__init__.py
nested_value_extractor.py
nested_value_extractor-0.2.0.dist-info/LICENSE
nested_value_extractor-0.2.0.dist-info/METADATA
nested_value_extractor-0.2.0.dist-info/WHEEL
nested_value_extractor-0.2.0.dist-info/top_level.txt
nested_value_extractor-0.2.0.dist-info/RECORD
