Metadata-Version: 2.1
Name: nested-value-extractor
Version: 0.2.0
Summary: Extract nested value from json-like dict by providing sequence of keys
Author-email: Ivan Livadnyi <morales_lamb_0y@icloud.com>
Project-URL: Homepage, https://github.com/skatromb/nested-dict-extractor
Classifier: Programming Language :: Python :: 3
Classifier: Operating System :: OS Independent
Requires-Python: >=3.10
License-File: LICENSE
